triyak_react_performance/__init__.py
triyak_react_performance/ai_optimizer.py
triyak_react_performance/bundle_optimizer.py
triyak_react_performance/core_web_vitals.py
triyak_react_performance/memory_optimizer.py
triyak_react_performance/performance_monitor.py
triyak_react_performance/performance_suite.py
triyak_react_performance-1.0.0.dist-info/METADATA
triyak_react_performance-1.0.0.dist-info/WHEEL
triyak_react_performance-1.0.0.dist-info/entry_points.txt
triyak_react_performance-1.0.0.dist-info/top_level.txt
triyak_react_performance-1.0.0.dist-info/RECORD
